
{
    "data": [
        {"id": "1000","EMPID": "EOO1","NAME": "Omesh Attal","description": "Product Description","Working_Hours": 50,"AGE": 24,"GENDER":"male"},
        {"id": "1001","EMPID": "E002","NAME": "Dhanashri Bhad","description": "Product Description","Working_Hours": 44,"AGE": 28,"GENDER":"female"},
        {"id": "1002","EMPID": "E003","NAME": "Dharshit Bhatt","description": "Product Description","Working_Hours": 45,"AGE": 26,"GENDER":"male"},
        {"id": "1003","EMPID": "E004","NAME": "Bhavya Ravani","description": "Product Description","Working_Hours": 50,"AGE": 25,"GENDER":"male"},
        {"id": "1004","EMPID": "E005","NAME": "Mayur Waghe","description": "Product Description","Working_Hours": 45,"AGE": 26,"GENDER":"male"},
        {"id": "1005","EMPID": "E006","NAME": "bhumit Javia","description": "Product Description","Working_Hours": 50,"AGE": 24,"GENDER":"male"},
        {"id": "1006","EMPID": "E007","NAME": "Dibyak Biswas","description": "Product Description","Working_Hours": 44,"AGE": 29,"GENDER":"male"},
        {"id": "1007","EMPID": "E008","NAME": "Abhay Thorat","description": "Product Description","Working_Hours": 45,"AGE": 23,"GENDER":"male"},
        {"id": "1008","EMPID": "E009","NAME": "Adesh Somwanshi","description": "Product Description","Working_Hours": 44,"AGE": 23,"GENDER":"male"},
        {"id": "1009","EMPID": "E010","NAME": "Nitin Ghyawat","description": "Product Description","Working_Hours": 50,"AGE": 25,"GENDER":"male"}
    ]
}
    